{
  "schemaVersion": 1,
  "id": "cursedcraft",
  "version": "${version}",

  "name": "cUrsedcraft",
  "description": "You will regret this mod",
  "authors": [
    "aww_shoot#8649"
  ],
  "contact": {
    "homepage": "https://fabricmc.net/",
    "sources": "https://github.com/FabricMC/fabric-example-mod"
  },

  "license": "CC0-1.0",
  "icon": "assets/cursedCraft/icon.png",

  "environment": "*",
  "entrypoints": {
    "main": [
      "net.cursedCraft.CursedCore"
    ]
  },
  "mixins": [
    "cursedCraft.mixins.json"
  ],

  "depends": {
    "fabricloader": ">=0.9.3",
    "fabric": "*",
    "minecraft": "1.16.x"
  },
  "suggests": {
    "flamingo": "*"
  }
}
